dacbench/__init__.py
dacbench/abstract_agent.py
dacbench/abstract_benchmark.py
dacbench/abstract_env.py
dacbench/argument_parsing.py
dacbench/logger.py
dacbench/plotting.py
dacbench/run_baselines.py
dacbench/runner.py
dacbench/additional_configs/fast_downward/fd_barman.json
dacbench/additional_configs/fast_downward/fd_blocksworld.json
dacbench/additional_configs/fast_downward/fd_childsnack.json
dacbench/additional_configs/fast_downward/fd_rovers.json
dacbench/additional_configs/fast_downward/fd_sokoban.json
dacbench/additional_configs/fast_downward/fd_visitall.json
dacbench/additional_configs/luby/luby_hard.json
dacbench/additional_configs/luby/luby_harder.json
dacbench/additional_configs/luby/luby_very_hard.json
dacbench/agents/__init__.py
dacbench/agents/dynamic_random_agent.py
dacbench/agents/generic_agent.py
dacbench/agents/simple_agents.py
dacbench/benchmarks/__init__.py
dacbench/benchmarks/cma_benchmark.py
dacbench/benchmarks/fast_downward_benchmark.py
dacbench/benchmarks/function_approximation_benchmark.py
dacbench/benchmarks/luby_benchmark.py
dacbench/benchmarks/sgd_benchmark.py
dacbench/benchmarks/theory_benchmark.py
dacbench/benchmarks/toysgd_benchmark.py
dacbench/container/Container Roadmap.md
dacbench/container/Containerized Benchmarks.md
dacbench/container/__init__.py
dacbench/container/architecture.png
dacbench/container/container_utils.py
dacbench/container/remote_env.py
dacbench/container/remote_runner.py
dacbench/container/singularity_recipes/cma.def
dacbench/container/singularity_recipes/dacbench.def
dacbench/container/singularity_recipes/recipe_template
dacbench/container/singularity_recipes/sgd.def
dacbench/container/singularity_recipes/theory.def
dacbench/envs/__init__.py
dacbench/envs/cma_es.py
dacbench/envs/fast_downward.py
dacbench/envs/function_approximation.py
dacbench/envs/luby.py
dacbench/envs/sgd.py
dacbench/envs/theory.py
dacbench/envs/toysgd.py
dacbench/envs/env_utils/__init__.py
dacbench/envs/env_utils/sgd_utils.py
dacbench-0.4.0.dist-info/licenses/LICENSE
dacbench-0.4.0.dist-info/METADATA
dacbench-0.4.0.dist-info/WHEEL
dacbench-0.4.0.dist-info/top_level.txt
dacbench-0.4.0.dist-info/RECORD
