Metadata-Version: 2.4
Name: DACBench
Version: 0.4.0
Summary: Dynamic Algorithm Configuration Benchmark
Author-email: Theresa Eimer <t.eimer@ai.uni-hannover.de>
License:                                  Apache License
Project-URL: Homepage, https://github.com/automl/DACBench
Project-URL: Documentation, https://automl.github.io/DACBench/main/
Project-URL: Repository, https://github.com/automl/DACBench
Project-URL: Issues, https://github.com/automl/DACBench/issues
Project-URL: Changelog, https://github.com/automl/DACBench/main/CHANGELOG.md
Keywords: DAC,Dynamic Algorithm Configuration,HPO
Classifier: Programming Language :: Python :: 3
Classifier: Natural Language :: English
Classifier: Environment :: Console
Classifier: Intended Audience :: Developers
Classifier: Intended Audience :: Education
Classifier: Intended Audience :: Science/Research
Classifier: License :: OSI Approved :: Apache Software License
Classifier: Operating System :: POSIX :: Linux
Classifier: Topic :: Scientific/Engineering :: Artificial Intelligence
Classifier: Topic :: Scientific/Engineering
Classifier: Topic :: Software Development
Requires-Python: >=3.10
License-File: LICENSE
Requires-Dist: gymnasium<=0.29.1
Requires-Dist: imageio~=2.35.1
Requires-Dist: numpy==1.26.4
Requires-Dist: pandas==2.2.3
Requires-Dist: matplotlib==3.9.2
Requires-Dist: seaborn==0.13.2
Requires-Dist: configspace~=1.2.1
Requires-Dist: scikit-learn==1.5.2
Requires-Dist: scipy==1.14.1
Requires-Dist: jupyter==1.0.0
Requires-Dist: Pyro4==4.82
Requires-Dist: ioh==0.3.17
Provides-Extra: dev
Requires-Dist: pytest==8.3.3; extra == "dev"
Requires-Dist: coverage[toml]==7.6.1; extra == "dev"
Requires-Dist: pre-commit==3.8.0; extra == "dev"
Requires-Dist: ruff==0.6.7; extra == "dev"
Provides-Extra: example
Requires-Dist: tabulate==0.9.0; extra == "example"
Requires-Dist: rich; extra == "example"
Provides-Extra: docs
Requires-Dist: automl-sphinx-theme==0.2.0; extra == "docs"
Provides-Extra: all
Requires-Dist: ioh==0.3.17; extra == "all"
Requires-Dist: modcma==1.0.8; extra == "all"
Requires-Dist: torchvision==0.19.1; extra == "all"
Requires-Dist: torch==2.4.1; extra == "all"
Requires-Dist: uuid; extra == "all"
Dynamic: license-file
